haru4me_poetry_demo/__init__.py
haru4me_poetry_demo/main.py
haru4me_poetry_demo-0.1.1.dist-info/WHEEL
haru4me_poetry_demo-0.1.1.dist-info/METADATA
haru4me_poetry_demo-0.1.1.dist-info/RECORD
