Metadata-Version: 2.1
Name: haru4me-poetry-demo
Version: 0.1.1
Summary: Poetry demo package
Author: Haru4me
Author-email: durdaev2010@yandex.ru
Requires-Python: >=3.9,<4.0
Classifier: Programming Language :: Python :: 3
Classifier: Programming Language :: Python :: 3.10
Classifier: Programming Language :: Python :: 3.9
Requires-Dist: numpy (>=1.23.1,<2.0.0)
Requires-Dist: pytest-reportlog (>=0.1.2,<0.2.0)
